fenda_weather/__init__.py
fenda_weather/server.py
fenda_weather-0.1.1.dist-info/METADATA
fenda_weather-0.1.1.dist-info/WHEEL
fenda_weather-0.1.1.dist-info/entry_points.txt
fenda_weather-0.1.1.dist-info/top_level.txt
fenda_weather-0.1.1.dist-info/RECORD
