Metadata-Version: 2.4
Name: fenda-weather
Version: 0.1.1
Summary: Add your description here
Author: fenda
Author-email: alashanprivate@163.com
Requires-Python: >=3.6
Requires-Dist: mcp[cli]>=1.9.0
Requires-Dist: setuptools>=80.7.1
Requires-Dist: twine>=6.1.0
Requires-Dist: wheel>=0.45.1
Dynamic: author
Dynamic: author-email
Dynamic: requires-python
